zwawright/__init__.py
zwawright/Tools/Compare.py
zwawright/Tools/RequestAndResponse.py
zwawright/Tools/Vardata.py
zwawright/Tools/__init__.py
zwawright/airtest/__init__.py
zwawright/airtest/__main__.py
zwawright/airtest/aircv/__init__.py
zwawright/airtest/aircv/aircv.py
zwawright/airtest/aircv/cal_confidence.py
zwawright/airtest/aircv/error.py
zwawright/airtest/aircv/keypoint_base.py
zwawright/airtest/aircv/keypoint_matching.py
zwawright/airtest/aircv/keypoint_matching_contrib.py
zwawright/airtest/aircv/multiscale_template_matching.py
zwawright/airtest/aircv/screen_recorder.py
zwawright/airtest/aircv/sift.py
zwawright/airtest/aircv/template.py
zwawright/airtest/aircv/template_matching.py
zwawright/airtest/aircv/utils.py
zwawright/airtest/cli/__init__.py
zwawright/airtest/cli/__main__.py
zwawright/airtest/cli/info.py
zwawright/airtest/cli/parser.py
zwawright/airtest/cli/runner.py
zwawright/airtest/core/__init__.py
zwawright/airtest/core/api.py
zwawright/airtest/core/assertions.py
zwawright/airtest/core/cv.py
zwawright/airtest/core/device.py
zwawright/airtest/core/error.py
zwawright/airtest/core/helper.py
zwawright/airtest/core/settings.py
zwawright/airtest/core/android/__init__.py
zwawright/airtest/core/android/adb.py
zwawright/airtest/core/android/android.py
zwawright/airtest/core/android/constant.py
zwawright/airtest/core/android/ime.py
zwawright/airtest/core/android/recorder.py
zwawright/airtest/core/android/rotation.py
zwawright/airtest/core/android/yosemite.py
zwawright/airtest/core/android/cap_methods/__init__.py
zwawright/airtest/core/android/cap_methods/adbcap.py
zwawright/airtest/core/android/cap_methods/base_cap.py
zwawright/airtest/core/android/cap_methods/javacap.py
zwawright/airtest/core/android/cap_methods/minicap.py
zwawright/airtest/core/android/cap_methods/screen_proxy.py
zwawright/airtest/core/android/touch_methods/__init__.py
zwawright/airtest/core/android/touch_methods/base_touch.py
zwawright/airtest/core/android/touch_methods/maxtouch.py
zazzywebatt-1.0.0.dist-info/METADATA
zazzywebatt-1.0.0.dist-info/WHEEL
zazzywebatt-1.0.0.dist-info/top_level.txt
zazzywebatt-1.0.0.dist-info/RECORD
