Metadata-Version: 2.1
Name: zazzywebatt
Version: 1.0.0
Summary: Easily cut the video by moviepy
Home-page: 
Author: zhangyuze
Author-email: zhangyuze1113@163.com
License: MIT
